{"layout": "4b067382-2daf-102c-9f4b-001c42dab01a", "name": "blank", "auth_required": false, "page_type": "8e4e0830-b991-4865-911e-49eeef586131", "navigation_entry": {"parent_id": null, "sequence": 2, "enabled": false, "name": "blank", "title": "blank"}, "data": {"data": {"lastSaved": 1411144146784, "palette": null, "layout": {"description": null, "id": "4b067382-2daf-102c-9f4b-001c42dab01a", "name": "layout_A"}, "name": "blank", "id": "8a4986ca4889458001488ebd768e4da1", "regions": [{"name": "sys_region_1", "dbId": "cfcc79a2-3dec-102c-9ad9-00163e000015", "properties": [], "defaultHeight": "400px", "components": [], "id": "sys_region_1", "desc": null}], "template": {"id": "cd487f33-4699-4a12-a925-2e2f1fa1f8ca", "name": "Skyline_v2", "properties": []}, "uniqueComponentIdList": [], "historicProperties": null, "type": "8e4e0830-b991-4865-911e-49eeef586131", "properties": [{"id": "402", "name": "meta.keywords", "v": ""}, {"id": "401", "name": "meta.description", "v": ""}, {"id": "105", "name": "body.background-attachment", "v": "scroll"}, {"id": "101", "name": "body.background-color", "v": null}, {"id": "102", "name": "body.background-image", "v": "//assets.yolacdn.net/template_assets/chaplin/resources/ba102c03-texture.png"}, {"id": "203", "name": "logo.visible", "v": null}, {"id": "202", "name": "logo.src", "v": null}, {"id": "501", "name": "heading.text", "v": "##page_heading##"}, {"id": "103", "name": "body.background-repeat", "v": "repeat"}, {"id": "201", "name": "logo.background-color", "v": null}, {"id": "104", "name": "body.background-position", "v": "bottom left"}, {"id": "602", "name": "banner.src", "v": ""}, {"id": "301", "name": "title.text", "v": "##page_heading##"}, {"id": "601", "name": "banner.background-color", "v": ""}, {"id": "904", "name": "heading.style", "v": null}, {"id": "52ffbfc7-7276-4ebe-9b73-38d45d548f4e", "name": "banner.display", "v": "none"}, {"id": "e2574746-aeac-4e27-8521-b128d1936a5f", "name": "layout.lock", "v": "false"}]}}, "id": "8a4986ca4889458001488ebd768e4da1"}